pid.v
module pid (
    input clk,
    input rst,
    input pid_start,
    input[15:0] data_in,
    output[15:0] data_out
);
    
    // states
    reg[2:0] state;
    localparam IDLE = 3'b000;
    localparam CALC_ERROR = 3'b001;
    localparam CALC_PID = 3'b010;
    localparam ADD_PID = 3'b011;
    localparam ADJUST_PID_VALUE = 3'b100;
    localparam OUTPUT_PID = 3'b101;

    // set point (the value PID tries to achieve)
    localparam setpoint = 54321;

    // pid constants (used for tuning)
    reg[15:0] kp = 10;
    reg[15:0] kd = 30;
    reg[15:0] ki = 1;
    
    // pid error
    reg[15:0] p = 0;
    reg[15:0] d = 0;
    reg[15:0] i = 0;

    // pid total
    reg[31:0] pid_total = 0;

    // intermediate data
    reg[15:0] inter_data = 0;

    // error and output
    reg[15:0] error = 0;
    reg[15:0] prev_error = 0;
    reg[15:0] out = 0;
    reg[15:0] prev_out = 0;

    always @ (posedge clk, posedge rst)
    begin
        if (rst)
        begin
            state = IDLE;
            p = 0;
            d = 0;
            i = 0;
        end else
        begin
            case (state)
                IDLE: 
                begin
                    inter_data <= data_in;
                    prev_error <= error;
                    prev_out <= out;

                    if (pid_start)
                        state <= CALC_ERROR;
                    else
                        state <= IDLE;
                end

                CALC_ERROR:
                begin
                    error <= setpoint - inter_data;

                    state <= CALC_PID;
                end

                CALC_PID:
                begin
                    p <= kp * error;
                    d <= kd * (error - prev_error);
                    i <= ki * (error + prev_error);

                    state <= ADD_PID;
                end

                ADD_PID:
                begin
                    pid_total <= prev_out + (p + i + d) / 2048; // output scaling with 2048

                    state <= ADJUST_PID_VALUE;
                end

                ADJUST_PID_VALUE:
                begin
                    if (pid_total > 65535)
                        pid_total <= 65535;
                    else if (pid_total < 1)
                        pid_total <= 1;

                    state <= OUTPUT_PID;
                end

                OUTPUT_PID:
                begin
                    out <= pid_total[15:0];

                    state <= IDLE;
                end
            endcase
        end
    end

    assign data_out = out;

endmodule

pid_tb.v
module pid_tb();

    initial begin
        $dumpfile("pid_tb.vcd");
        $dumpvars(0, pid_tb);
    end

    integer i;
    reg clk = 0;
    initial begin
        for (i = 0; i < 80; i++)
            #1 clk = ~clk;
    end

    reg pid_start;
    reg[15:0] data_in;
    wire[15:0] data_out;
    pid uut(
        .clk(clk),
        .rst(rst),
        .pid_start(pid_start),
        .data_in(data_in),
        .data_out(data_out)
    );

    reg rst;
    initial begin
        pid_start = 0;
        data_in = 0;

        // pulse reset signal
        rst = 1;
        #1
        rst = 0;

        #5
        
        // test 1 (no error)
        data_in = 16'd54321;
        #1
        pid_start = 1'b1;
        #2
        pid_start = 1'b0;

        #15

        // test 2 (negative error)
        data_in = 16'd56000;
        #1
        pid_start = 1'b1;
        #2
        pid_start = 1'b0;

        #15

        // test 3 (positive error)
        data_in = 16'd52000;
        #1
        pid_start = 1'b1;
        #2
        pid_start = 1'b0;

        #15

        rst = 1;
    end

endmodule

pid_tb.vcd
$date
	Mon May 27 12:01:01 2024
$end
$version
	Icarus Verilog
$end
$timescale
	1ps
$end
$scope module pid_tb $end
$var wire 16 ! data_out [15:0] $end
$var reg 1 " clk $end
$var reg 16 # data_in [15:0] $end
$var reg 1 $ pid_start $end
$var reg 1 % rst $end
$var integer 32 & i [31:0] $end
$scope module uut $end
$var wire 1 " clk $end
$var wire 16 ' data_in [15:0] $end
$var wire 16 ( data_out [15:0] $end
$var wire 1 $ pid_start $end
$var wire 1 % rst $end
$var reg 16 ) d [15:0] $end
$var reg 16 * error [15:0] $end
$var reg 16 + i [15:0] $end
$var reg 16 , inter_data [15:0] $end
$var reg 16 - kd [15:0] $end
$var reg 16 . ki [15:0] $end
$var reg 16 / kp [15:0] $end
$var reg 16 0 out [15:0] $end
$var reg 16 1 p [15:0] $end
$var reg 32 2 pid_total [31:0] $end
$var reg 16 3 prev_error [15:0] $end
$var reg 16 4 prev_out [15:0] $end
$var reg 3 5 state [2:0] $end
$upscope $end
$upscope $end
$enddefinitions $end
#0
$dumpvars
b0 5
b0 4
b0 3
b0 2
b0 1
b0 0
b1010 /
b1 .
b11110 -
b0 ,
b0 +
b0 *
b0 )
b0 (
b0 '
b0 &
1%
0$
b0 #
0"
b0 !
$end
#1
0%
b1 &
1"
#2
b10 &
0"
#3
b11 &
1"
#4
b100 &
0"
#5
b101 &
1"
#6
b110 &
0"
b1101010000110001 #
b1101010000110001 '
#7
b1 5
b1101010000110001 ,
b111 &
1"
1$
#8
b1000 &
0"
#9
b10 5
b1001 &
1"
0$
#10
b1010 &
0"
#11
b11 5
b1011 &
1"
#12
b1100 &
0"
#13
b100 5
b1101 &
1"
#14
b1110 &
0"
#15
b101 5
b1 2
b1111 &
1"
#16
b10000 &
0"
#17
b0 5
b1 !
b1 (
b1 0
b10001 &
1"
#18
b10010 &
0"
#19
b1 4
b10011 &
1"
#20
b10100 &
0"
#21
b10101 &
1"
#22
b10110 &
0"
#23
b10111 &
1"
#24
b11000 &
0"
b1101101011000000 #
b1101101011000000 '
#25
b1 5
b1101101011000000 ,
b11001 &
1"
1$
#26
b11010 &
0"
#27
b10 5
b1111100101110001 *
b11011 &
1"
0$
#28
b11100 &
0"
#29
b11 5
b1111100101110001 +
b11101100111110 )
b1011111001101010 1
b11101 &
1"
#30
b11110 &
0"
#31
b100 5
b111111 2
b11111 &
1"
#32
b100000 &
0"
#33
b101 5
b100001 &
1"
#34
b100010 &
0"
#35
b0 5
b111111 !
b111111 (
b111111 0
b100011 &
1"
#36
b100100 &
0"
#37
b111111 4
b1111100101110001 3
b100101 &
1"
#38
b100110 &
0"
#39
b100111 &
1"
#40
b101000 &
0"
#41
b101001 &
1"
#42
b101010 &
0"
b1100101100100000 #
b1100101100100000 '
#43
b1 5
b1100101100100000 ,
b101011 &
1"
1$
#44
b101100 &
0"
#45
b10 5
b100100010001 *
b101101 &
1"
0$
#46
b101110 &
0"
#47
b11 5
b1010000010 +
b1101010011000000 )
b101101010101010 1
b101111 &
1"
#48
b110000 &
0"
#49
b100 5
b1100101 2
b110001 &
1"
#50
b110010 &
0"
#51
b101 5
b110011 &
1"
#52
b110100 &
0"
#53
b0 5
b1100101 !
b1100101 (
b1100101 0
b110101 &
1"
#54
b110110 &
0"
#55
b1100101 4
b100100010001 3
b110111 &
1"
#56
b111000 &
0"
#57
b111001 &
1"
#58
b111010 &
0"
#59
b111011 &
1"
#60
b0 +
b0 )
b0 1
b111100 &
0"
1%
#61
b111101 &
1"
#62
b111110 &
0"
#63
b111111 &
1"
#64
b1000000 &
0"
#65
b1000001 &
1"
#66
b1000010 &
0"
#67
b1000011 &
1"
#68
b1000100 &
0"
#69
b1000101 &
1"
#70
b1000110 &
0"
#71
b1000111 &
1"
#72
b1001000 &
0"
#73
b1001001 &
1"
#74
b1001010 &
0"
#75
b1001011 &
1"
#76
b1001100 &
0"
#77
b1001101 &
1"
#78
b1001110 &
0"
#79
b1001111 &
1"
#80
b1010000 &
0"
